ggpubpy/__init__.py
ggpubpy/alluvialplot.py
ggpubpy/bland_altman.py
ggpubpy/boxplot.py
ggpubpy/correlation_matrix.py
ggpubpy/datasets.py
ggpubpy/helper.py
ggpubpy/plots.py
ggpubpy/qqplot.py
ggpubpy/shiftplot.py
ggpubpy/violinplot.py
ggpubpy/data/iris.csv
ggpubpy/data/titanic.csv
ggpubpy-0.5.1.dist-info/licenses/LICENSE
ggpubpy-0.5.1.dist-info/METADATA
ggpubpy-0.5.1.dist-info/WHEEL
ggpubpy-0.5.1.dist-info/top_level.txt
ggpubpy-0.5.1.dist-info/RECORD
