Metadata-Version: 2.4
Name: ggpubpy
Version: 0.5.1
Summary: matplotlib Based Publication-Ready Plots with Statistical Tests
Author-email: Turkalp Akbasli <akbaslint@gmail.com>
Maintainer-email: Turkalp Akbasli <akbaslint@gmail.com>
License: MIT License
Project-URL: Homepage, https://github.com/turkalpmd/ggpubpy
Project-URL: Repository, https://github.com/turkalpmd/ggpubpy.git
Project-URL: Documentation, https://ggpubpy.readthedocs.io
Project-URL: Bug Tracker, https://github.com/turkalpmd/ggpubpy/issues
Project-URL: Source Code, https://github.com/turkalpmd/ggpubpy
Project-URL: Download, https://pypi.org/project/ggpubpy/#files
Keywords: matplotlib,plotting,visualization,statistics,publication,ggplot,data-science,alluvial,flow-diagram,correlation-matrix,boxplot,violin-plot,shift-plot
Classifier: Development Status :: 4 - Beta
Classifier: Intended Audience :: Science/Research
Classifier: Intended Audience :: Developers
Classifier: License :: OSI Approved :: MIT License
Classifier: Operating System :: OS Independent
Classifier: Programming Language :: Python :: 3
Classifier: Programming Language :: Python :: 3.8
Classifier: Programming Language :: Python :: 3.9
Classifier: Programming Language :: Python :: 3.10
Classifier: Programming Language :: Python :: 3.11
Classifier: Programming Language :: Python :: 3.12
Classifier: Topic :: Scientific/Engineering :: Visualization
Classifier: Topic :: Scientific/Engineering :: Information Analysis
Classifier: Topic :: Software Development :: Libraries :: Python Modules
Classifier: Framework :: Matplotlib
Requires-Python: >=3.8
License-File: LICENSE
Requires-Dist: numpy>=1.20.0
Requires-Dist: pandas>=1.3.0
Requires-Dist: matplotlib>=3.5.0
Requires-Dist: scipy>=1.7.0
Provides-Extra: dev
Requires-Dist: pytest>=7.0.0; extra == "dev"
Requires-Dist: pytest-cov>=4.0.0; extra == "dev"
Requires-Dist: black>=22.0.0; extra == "dev"
Requires-Dist: flake8>=5.0.0; extra == "dev"
Requires-Dist: isort>=5.10.0; extra == "dev"
Requires-Dist: mypy>=0.991; extra == "dev"
Requires-Dist: pre-commit>=2.20.0; extra == "dev"
Requires-Dist: twine>=4.0.0; extra == "dev"
Requires-Dist: build>=0.8.0; extra == "dev"
Provides-Extra: docs
Requires-Dist: sphinx>=4.0.0; extra == "docs"
Requires-Dist: sphinx-rtd-theme>=1.0.0; extra == "docs"
Requires-Dist: myst-parser>=0.18.0; extra == "docs"
Requires-Dist: sphinx-autodoc-typehints>=1.12.0; extra == "docs"
Requires-Dist: linkify-it-py>=2.0.0; extra == "docs"
Provides-Extra: examples
Requires-Dist: seaborn>=0.11.0; extra == "examples"
Requires-Dist: jupyter>=1.0.0; extra == "examples"
Requires-Dist: notebook>=6.4.0; extra == "examples"
Dynamic: license-file
